[{ "type": "motivation",
  "header": "Motivation 1",
  "text": "Lorem ipsum dolor sit amet, consectetur adipiscing elit. Duis et turpis eget tellus pellentesque bibendum. Aliquam cursus massa vehicula est posuere, semper sodales tellus bibendum. Nam id hendrerit ex, vitae euismod velit. Sed in consectetur purus." },
 { "type": "motivation",
  "header": "Motivation 2",
  "text": "" },
  { "type": "project",
  "header": "Project 1",
  "tech": ["AngularJS", "JavasScript"],
  "text": "Testing asdsadsa" },
 { "type": "project",
  "header": "Project 2",
  "text": "" },
 { "type": "project",
  "header": "Project 3",
  "text": "" },
 { "type": "project",
  "header": "Project 4",
  "text": "" }
]